PyAutoMaker/__init__.py
PyAutoMaker/arduino.py
PyAutoMaker/class_dd.py
PyAutoMaker/darknet.py
PyAutoMaker/exception.py
PyAutoMaker/image.py
PyAutoMaker/input.py
PyAutoMaker/input_base.py
PyAutoMaker/tensor.py
PyAutoMaker/utils.py
PyAutoMaker/dlls/DD64.dll
PyAutoMaker/dlls/ImageDLL.dll
PyAutoMaker/dlls/opencv_world455.dll
PyAutoMaker-0.3.0.dist-info/LICENSE
PyAutoMaker-0.3.0.dist-info/METADATA
PyAutoMaker-0.3.0.dist-info/WHEEL
PyAutoMaker-0.3.0.dist-info/top_level.txt
PyAutoMaker-0.3.0.dist-info/RECORD
