Metadata-Version: 2.1
Name: PyAutoMaker
Version: 0.3.0
Summary: 자동화를 위한 패키지
Home-page: https://github.com/boa9448/PyAutoMaker
Author: WDW
Author-email: boa9448@naver.com
License: UNKNOWN
Platform: UNKNOWN
Classifier: Programming Language :: Python :: 3
Classifier: License :: OSI Approved :: MIT License
Classifier: Operating System :: Microsoft :: Windows :: Windows 10
Requires-Python: >=3.7
License-File: LICENSE
Requires-Dist: psutil
Requires-Dist: pywin32
Requires-Dist: opencv-contrib-python
Requires-Dist: pySerial
Requires-Dist: PySide6
Requires-Dist: qt-material
